x_api/__init__.py
x_api/api.py
xn_api-1.0.4.dist-info/METADATA
xn_api-1.0.4.dist-info/WHEEL
xn_api-1.0.4.dist-info/top_level.txt
xn_api-1.0.4.dist-info/RECORD
