Metadata-Version: 2.1
Name: xn-api
Version: 1.0.4
Summary: Simplest fastest minimal REST API CRUD generator for Tortoise ORM models
Author-email: Artemiev <mixartemev@gmail.com>
License: MIT
Project-URL: Homepage, https://github.com/XyncNet/x-api
Project-URL: Repository, https://github.com/XyncNet/x-api
Keywords: starlette,fastapi,admin,generator,db-model,crud,tortoise-orm,ASGI-admin
Requires-Python: >=3.12
Requires-Dist: fastapi
Requires-Dist: uvicorn
Requires-Dist: xn-model
Provides-Extra: auth
Requires-Dist: xn-auth ; extra == 'auth'
Provides-Extra: auth-pswd
Requires-Dist: pswd-auth ; extra == 'auth-pswd'
Provides-Extra: auth-tg
Requires-Dist: xtg-auth ; extra == 'auth-tg'
Provides-Extra: dev
Requires-Dist: build ; extra == 'dev'
Requires-Dist: python-dotenv ; extra == 'dev'
Requires-Dist: twine ; extra == 'dev'
